setup.py
distributions/Binomialdistribution.py
distributions/Gaussiandistribution.py
distributions/Generaldistribution.py
distributions/__init__.py
distributions0.1.egg-info/PKG-INFO
distributions0.1.egg-info/SOURCES.txt
distributions0.1.egg-info/dependency_links.txt
distributions0.1.egg-info/not-zip-safe
distributions0.1.egg-info/top_level.txt